django_env_validator/__init__.py
django_env_validator/apps.py
django_env_validator/validator.py
django_env_validator-1.0.1.dist-info/LICENSE
django_env_validator-1.0.1.dist-info/METADATA
django_env_validator-1.0.1.dist-info/WHEEL
django_env_validator-1.0.1.dist-info/top_level.txt
django_env_validator-1.0.1.dist-info/RECORD
